LICENSE
MANIFEST.in
README.markdown
requirements.txt
setup.py
webdriverplus/__init__.py
webdriverplus/deprecation.py
webdriverplus/orderedset.py
webdriverplus/selectors.py
webdriverplus/utils.py
webdriverplus/webdriver.py
webdriverplus/webelement.py
webdriverplus/webelementset.py
webdriverplus/wrappers.py
webdriverplus.egg-info/PKG-INFO
webdriverplus.egg-info/SOURCES.txt
webdriverplus.egg-info/dependency_links.txt
webdriverplus.egg-info/requires.txt
webdriverplus.egg-info/top_level.txt