Metadata-Version: 1.0
Name: webdriverplus
Version: 0.1.5
Summary: WebDriver Plus.
Home-page: http://webdriverplus.org
Author: Tom Christie
Author-email: UNKNOWN
License: BSD
Platform: UNKNOWN
